CHANGELOG.rst
LICENSE.txt
MANIFEST.in
README.rst
setup.py
Flask_Geckoboard.egg-info/PKG-INFO
Flask_Geckoboard.egg-info/SOURCES.txt
Flask_Geckoboard.egg-info/dependency_links.txt
Flask_Geckoboard.egg-info/requires.txt
Flask_Geckoboard.egg-info/top_level.txt
flask_geckoboard/__init__.py
flask_geckoboard/decorators.py
tests/__init__.py
tests/settings.py
tests/test_decorators.py
tests/utils.py