Metadata-Version: 1.1
Name: Flask-Geckoboard
Version: 0.1.0
Summary: Geckoboard custom widgets for Flask projects
Home-page: http://github.com/PolymathVentures/flask-geckoboard
Author: Rob Eroh
Author-email: rob@eroh.me
License: MIT License
Download-URL: http://github.com/PolymathVentures/flask-geckoboard/archives/master
Keywords: flask,geckoboard
Platform: any
Classifier: Development Status :: 4 - Beta
Classifier: Environment :: Web Environment
Classifier: Framework :: Flask
Classifier: Intended Audience :: Developers
Classifier: License :: OSI Approved :: MIT License
Classifier: Operating System :: OS Independent
Classifier: Programming Language :: Python
Classifier: Topic :: Internet :: WWW/HTTP
Classifier: Topic :: Software Development :: Libraries :: Python Modules
